[
	{
		"constant": true,
		"inputs": [
			{
				"name": "",
				"type": "address"
			},
			{
				"name": "",
				"type": "uint256"
			}
		],
		"name": "hashData",
		"outputs": [
			{
				"name": "",
				"type": "string"
			}
		],
		"payable": false,
		"stateMutability": "view",
		"type": "function"
	},
	{
		"constant": true,
		"inputs": [
			{
				"name": "_from",
				"type": "address"
			}
		],
		"name": "getData",
		"outputs": [
			{
				"name": "",
				"type": "string"
			}
		],
		"payable": false,
		"stateMutability": "view",
		"type": "function"
	},
	{
		"constant": false,
		"inputs": [
			{
				"name": "data",
				"type": "string"
			}
		],
		"name": "store",
		"outputs": [],
		"payable": false,
		"stateMutability": "nonpayable",
		"type": "function"
	}
]